mitsubishi_monitor/__init__.py
mitsubishi_monitor/const.py
mitsubishi_monitor/monitor.py
mitsubishi_monitor/util.py
mitsubishi_monitor-1.1.0.dist-info/METADATA
mitsubishi_monitor-1.1.0.dist-info/WHEEL
mitsubishi_monitor-1.1.0.dist-info/top_level.txt
mitsubishi_monitor-1.1.0.dist-info/RECORD
