Metadata-Version: 2.1
Name: mitsubishi-monitor
Version: 1.1.0
Author: Roland Zitny
